<?xml version="1.0" encoding="utf-8"?>
<SoundBanksInfo Platform="Windows" BasePlatform="Windows" SchemaVersion="16" SoundBankVersion="145">
	<RootPaths>
		<ProjectRoot>../..</ProjectRoot>
		<SourceFilesRoot>../../.cache/Windows/</SourceFilesRoot>
		<SoundBanksRoot>.</SoundBanksRoot>
		<ExternalSourcesInputFile></ExternalSourcesInputFile>
		<ExternalSourcesOutputRoot>.</ExternalSourcesOutputRoot>
	</RootPaths>
	<DialogueEvents/>
	<SoundBanks>
		<SoundBank Id="1355168291" Type="User" Language="SFX" Hash="{986487A9-2683-E47A-8688-3D0FE6FDB954}">
			<ShortName>Init</ShortName>
			<Path>Init.bnk</Path>
			<Plugins>
				<AudioDevices>
					<Plugin Id="2317455096" Name="No_Output" LibName="No Output" LibId="11862023"/>
					<Plugin Id="3859886410" Name="System" LibName="System" LibId="11403271"/>
				</AudioDevices>
			</Plugins>
			<Busses>
				<Bus Id="3803692087" Name="Master Audio Bus"/>
			</Busses>
		</SoundBank>
		<SoundBank Id="3898083304" Type="User" Language="SFX" Hash="{D71B1821-E4E3-A464-923A-8414B2314BDC}">
			<ShortName>SoundEffects</ShortName>
			<Path>SoundEffects.bnk</Path>
		</SoundBank>
	</SoundBanks>
	<FileHash>{C787A846-3C72-4780-E8B3-88C8B0B91ADB}</FileHash>
</SoundBanksInfo>
